ofsc/__init__.py
ofsc/capacity.py
ofsc/common.py
ofsc/core.py
ofsc/exceptions.py
ofsc/metadata.py
ofsc/models.py
ofsc/oauth.py
ofsc/async_client/__init__.py
ofsc/async_client/capacity.py
ofsc/async_client/core.py
ofsc/async_client/metadata.py
ofsc/async_client/oauth.py
ofsc-2.21.0.dist-info/METADATA
ofsc-2.21.0.dist-info/WHEEL
ofsc-2.21.0.dist-info/licenses/LICENSE.txt
ofsc-2.21.0.dist-info/RECORD
