Metadata-Version: 2.4
Name: ofsc
Version: 2.21.0
Summary: Python wrapper for Oracle Field Service API
Project-URL: Repository, https://github.com/btoron/pyOFSC
Author-email: Borja Toron <borja.toron@gmail.com>
License-Expression: MIT
License-File: LICENSE.txt
Requires-Python: ~=3.11.0
Requires-Dist: cachetools<6,>=5.3.1
Requires-Dist: httpx[http2]<1,>=0.27.0
Requires-Dist: pydantic-settings<3,>=2.2.1
Requires-Dist: pydantic<3,>=2.6.3
Requires-Dist: requests<3,>=2.28.1
